nhsnumber/__init__.py
nhssums/__init__.py
nhssums-0.1.2.dist-info/LICENSE
nhssums-0.1.2.dist-info/METADATA
nhssums-0.1.2.dist-info/WHEEL
nhssums-0.1.2.dist-info/top_level.txt
nhssums-0.1.2.dist-info/RECORD
