Metadata-Version: 2.1
Name: nhssums
Version: 0.1.2
Summary: A small package to perform checksum validation on NHS numbers.
Home-page: https://github.com/sellorm/nhsnumber-python
Author: Mark Sellors
Author-email: python@5vcc.com
License: UNKNOWN
Platform: UNKNOWN
Classifier: Programming Language :: Python :: 3
Classifier: License :: OSI Approved :: MIT License
Classifier: Operating System :: OS Independent
Requires-Python: >=3.6
License-File: LICENSE
